{"body": "◉_◉", "gilded": 0, "created_utc": "1301890349", "subreddit": "RUGC_Midwest", "score": 1, "controversiality": 0}
{"body": "◉_◉", "gilded": 0, "created_utc": "1301893529", "subreddit": "funny", "score": 6, "controversiality": 0}
{"body": "maybe she got hooked up with some fucking incredible seats to a Champions League game? ¯\\_(ツ)_/¯", "gilded": 0, "created_utc": "1302462120", "subreddit": "sex", "score": 8, "controversiality": 0}
{"body": "Gee, what else has she done... [imdb](http://www.imdb.com/name/nm1559611/)... A whole lot of Stephanie from LazyTown and a short called A Fix, huh? Let's watch the [trailer](http://www.imdb.com/video/wab/vi2525233945/).\n\n◉_◉\n\nEdit: typo", "gilded": 0, "created_utc": "1303833232", "subreddit": "videos", "score": 8, "controversiality": 0}
